WSGIEchoIP/__init__.py
WSGIEchoIP-1.1.1.dist-info/LICENSE
WSGIEchoIP-1.1.1.dist-info/METADATA
WSGIEchoIP-1.1.1.dist-info/WHEEL
WSGIEchoIP-1.1.1.dist-info/top_level.txt
WSGIEchoIP-1.1.1.dist-info/RECORD
