Metadata-Version: 2.1
Name: WSGIEchoIP
Version: 1.1.1
Summary: A simple WSGI app that returns the value of the `X-Forwarded-For` header
License:                     GNU GENERAL PUBLIC LICENSE
Project-URL: Homepage, https://github.com/jb2170/WSGIEchoIP/
License-File: LICENSE
